<EnterpriseDocument InterfaceName="ManageSpecialsImport" CreationSource="Speedway Default" Version="1.0.0" CreationTimestamp="2018-07-19T21:00:00"><RetailerReference ClientIdentifierType="ClientID" ClientIdentifier="10000001" /><SpecialList><Special specialName="CV4 - RIVERCIT MI 2/$13" specialXRefID="1163673" specialReceiptText="2/$13" priorityRanking="0" requiresLoyalty="n" startDate="2019-08-05"><QualifierList><Qualifier retailItemGroupName="401 - RIVERCIT MI 2/$13" minimumIdentifier="Quantity" minimumValue="2" discountType="Set Retail" discountValue="13.00" taxReduced="y" /></QualifierList></Special></SpecialList></EnterpriseDocument>
