<EnterpriseDocument InterfaceName="ManageSpecialsImport" CreationSource="Speedway Default" Version="1.0.0" CreationTimestamp="2018-07-19T21:00:00"><RetailerReference ClientIdentifierType="ClientID" ClientIdentifier="10000001" /><SpecialList><Special specialName="GC6 THEATRE BOX EDLP 2F3.33" specialXRefID="1163595" specialReceiptText="THEATRE BOX 2F3.33" priorityRanking="10" requiresLoyalty="n" startDate="2019-07-30"><QualifierList><Qualifier retailItemGroupName="consum-THEATER BOX EDLP 5Z" minimumIdentifier="Quantity" minimumValue="2" discountType="Set Retail" discountValue="3.33" taxReduced="y" /></QualifierList></Special></SpecialList></EnterpriseDocument>
