<RadiantDocument Name="RadiantSupplierCatalog"><CatalogReference Mode="Update"><SupplierReference SupplierName="F VONHANSN - VON HANSON'S" SupplierIdentifierType="XRefID" SupplierIdentifier="VONHANSN" /><RetailerReference ClientName="Client" ClientIdentifierType="ClientID" ClientIdentifier="10000001" /></CatalogReference><SupplierItemList><SupplierItem Name="VH DILL RANCH PRETZELS" ProductCode="858814007001" XRefID="36010442" InventoryItemExternalID="36010442" Status="a" SupplierItemGroupName="601 04B 000" SupplierPackageUOM="Case" QuantityFactor="27"><BarcodeList><Barcode TypeCode="u" Number="858814007001" /></BarcodeList><CostList><Cost CostLevel="Master" PackageCost="0" Allowance="0" /><Cost CostLevel="Franchise" PackageCost="0" Allowance="0" /><Cost CostLevel="DO Hasty Truck Stop Inc" PackageCost="1.33" Allowance="0" CostStartDate="2019-04-09" /></CostList></SupplierItem><SupplierItem Name="VH PARMESAN PRETZELS" ProductCode="858814007018" XRefID="36010444" InventoryItemExternalID="36010444" Status="a" SupplierItemGroupName="601 04B 000" SupplierPackageUOM="Case" QuantityFactor="27"><BarcodeList><Barcode TypeCode="u" Number="858814007018" /></BarcodeList><CostList><Cost CostLevel="Master" PackageCost="0" Allowance="0" /><Cost CostLevel="Franchise" PackageCost="0" Allowance="0" /><Cost CostLevel="DO Hasty Truck Stop Inc" PackageCost="1.33" Allowance="0" CostStartDate="2019-04-09" /></CostList></SupplierItem><SupplierItem Name="VH CINNAMON CRUNCH PRETZELS" ProductCode="858814007025" XRefID="36010441" InventoryItemExternalID="36010441" Status="a" SupplierItemGroupName="601 04B 000" SupplierPackageUOM="Case" QuantityFactor="24"><BarcodeList><Barcode TypeCode="u" Number="858814007025" /></BarcodeList><CostList><Cost CostLevel="Master" PackageCost="0" Allowance="0" /><Cost CostLevel="Franchise" PackageCost="0" Allowance="0" /><Cost CostLevel="DO Hasty Truck Stop Inc" PackageCost="1.5" Allowance="0" CostStartDate="2019-04-09" /></CostList></SupplierItem><SupplierItem Name="VH HOT BUFFALO PRETZELS" ProductCode="858814007032" XRefID="36010443" InventoryItemExternalID="36010443" Status="a" SupplierItemGroupName="601 04B 000" SupplierPackageUOM="Case" QuantityFactor="27"><BarcodeList><Barcode TypeCode="u" Number="858814007032" /></BarcodeList><CostList><Cost CostLevel="Master" PackageCost="0" Allowance="0" /><Cost CostLevel="Franchise" PackageCost="0" Allowance="0" /><Cost CostLevel="DO Hasty Truck Stop Inc" PackageCost="1.33" Allowance="0" CostStartDate="2019-04-09" /></CostList></SupplierItem><SupplierItem Name="VH TANGY MUSTARD PRETZELS" ProductCode="858814007049" XRefID="36010445" InventoryItemExternalID="36010445" Status="a" SupplierItemGroupName="601 04B 000" SupplierPackageUOM="Case" QuantityFactor="27"><BarcodeList><Barcode TypeCode="u" Number="858814007049" /></BarcodeList><CostList><Cost CostLevel="Master" PackageCost="0" Allowance="0" /><Cost CostLevel="Franchise" PackageCost="0" Allowance="0" /><Cost CostLevel="DO Hasty Truck Stop Inc" PackageCost="1.33" Allowance="0" CostStartDate="2019-04-09" /></CostList></SupplierItem></SupplierItemList></RadiantDocument>
